Metadata-Version: 2.1
Name: odoo-addon-stock_quant_package_dimension
Version: 18.0.1.0.1.1
Requires-Python: >=3.10
Requires-Dist: odoo-addon-product_packaging_dimension==18.0.*
Requires-Dist: odoo-addon-stock_quant_package_product_packaging==18.0.*
Requires-Dist: odoo==18.0.*
Summary: Use dimensions on packages
Home-page: https://github.com/OCA/stock-logistics-tracking
License: AGPL-3
Author: Camptocamp, Odoo Community Association (OCA)
Author-email: support@odoo-community.org
Classifier: Programming Language :: Python
Classifier: Framework :: Odoo
Classifier: Framework :: Odoo :: 18.0
Classifier: License :: OSI Approved :: GNU Affero General Public License v3
Classifier: Development Status :: 4 - Beta
